odoo/addons/account_invoice_report_picking_customer_note/README.rst
odoo/addons/account_invoice_report_picking_customer_note/__init__.py
odoo/addons/account_invoice_report_picking_customer_note/__manifest__.py
odoo/addons/account_invoice_report_picking_customer_note/i18n/account_invoice_report_picking_customer_note.pot
odoo/addons/account_invoice_report_picking_customer_note/i18n/es.po
odoo/addons/account_invoice_report_picking_customer_note/i18n/it.po
odoo/addons/account_invoice_report_picking_customer_note/readme/CONTEXT.rst
odoo/addons/account_invoice_report_picking_customer_note/readme/CONTRIBUTORS.rst
odoo/addons/account_invoice_report_picking_customer_note/readme/DESCRIPTION.rst
odoo/addons/account_invoice_report_picking_customer_note/readme/USAGE.rst
odoo/addons/account_invoice_report_picking_customer_note/static/description/icon.png
odoo/addons/account_invoice_report_picking_customer_note/static/description/index.html
odoo/addons/account_invoice_report_picking_customer_note/tests/__init__.py
odoo/addons/account_invoice_report_picking_customer_note/tests/test_print_picking_customer_note.py
odoo/addons/account_invoice_report_picking_customer_note/views/account_invoice_report.xml
odoo_addon_account_invoice_report_picking_customer_note-16.0.1.0.1.2.dist-info/METADATA
odoo_addon_account_invoice_report_picking_customer_note-16.0.1.0.1.2.dist-info/WHEEL
odoo_addon_account_invoice_report_picking_customer_note-16.0.1.0.1.2.dist-info/top_level.txt
odoo_addon_account_invoice_report_picking_customer_note-16.0.1.0.1.2.dist-info/RECORD
