Metadata-Version: 2.1
Name: odoo-addon-account_invoice_report_picking_customer_note
Version: 16.0.1.0.1.2
Summary: Print picking customer note in Invoice
Home-page: https://github.com/OCA/account-invoice-reporting
Author: Moduon, Odoo Community Association (OCA)
Author-email: support@odoo-community.org
License: AGPL-3
Classifier: Programming Language :: Python
Classifier: Framework :: Odoo
Classifier: Framework :: Odoo :: 16.0
Classifier: License :: OSI Approved :: GNU Affero General Public License v3
Requires-Python: >=3.10
Requires-Dist: odoo-addon-sale-stock-picking-note<16.1dev,>=16.0dev
Requires-Dist: odoo<16.1dev,>=16.0a
